{
    "@context": [
        "/wiki/Category:OSWb58cb5a4654f52e1804c74c035d21352?action=raw&slot=jsonschema",
        {}
    ],
    "$defs": {
        "generated": {
            "$comment": "Autogenerated section - do not edit. Generated from Category:Category Category:OSWffe74f291d354037b318c422591c5023 Category:OSWac07a46c2cf14f3daec503136861f5ab",
            "allOf": [
                {
                    "$ref": "/wiki/Category:OSWb58cb5a4654f52e1804c74c035d21352?action=raw&slot=jsonschema"
                }
            ],
            "type": "object",
            "uuid": "0301595d-3ef3-5fcb-98b6-3e87d8b3d34c",
            "title": "GeneratedTotalPressure",
            "title*": {
                "en": "Total Pressure"
            },
            "description": "This is an autogenerated partial class definition of 'TotalPressure'",
            "description*": {
                "en": "The total pressure is the sum of the dynamic and static pressures, that is $P_0 = P + q$."
            },
            "required": [
                "type"
            ],
            "properties": {
                "type": {
                    "default": [
                        "Category:OSW0301595d3ef35fcb98b63e87d8b3d34c"
                    ]
                }
            },
            "defaultProperties": [
                "type"
            ],
            "x-smw-quantity-property": "Property:HasTotalPressureValue"
        }
    },
    "allOf": [
        {
            "$ref": "#/$defs/generated"
        }
    ],
    "title": "TotalPressure",
    "description": "The total pressure is the sum of the dynamic and static pressures, that is $P_0 = P + q$."
}