{
    "@context": [
        "/wiki/Category:OSW4082937906634af992cf9a1b18d772cf?action=raw&slot=jsonschema",
        {}
    ],
    "$defs": {
        "generated": {
            "$comment": "Autogenerated section - do not edit. Generated from Category:Category Category:OSWffe74f291d354037b318c422591c5023 Category:OSWc7f9aec4f71f4346b6031f96d7e46bd7",
            "allOf": [
                {
                    "$ref": "/wiki/Category:OSW4082937906634af992cf9a1b18d772cf?action=raw&slot=jsonschema"
                }
            ],
            "type": "object",
            "uuid": "1c930bb3-24ca-5e5b-84c2-5be2079b2d21",
            "title": "GeneratedBulkModulus",
            "title*": {
                "en": "Bulk Modulus"
            },
            "description": "This is an autogenerated partial class definition of 'BulkModulus'",
            "description*": {
                "en": "The bulk modulus of a substance measures the substance's resistance to uniform compression. It is defined as the ratio of the infinitesimal pressure increase to the resulting relative decrease of the volume."
            },
            "required": [
                "type"
            ],
            "properties": {
                "type": {
                    "default": [
                        "Category:OSW1c930bb324ca5e5b84c25be2079b2d21"
                    ]
                },
                "unit": {
                    "title": "BulkModulusUnit",
                    "enum": [
                        "Item:OSWb663e6bff3595e7b93b28fffce66c50c",
                        "Item:OSWb663e6bff3595e7b93b28fffce66c50c#OSW49bb4743a5735e189777f3c6bd422a52",
                        "Item:OSWb663e6bff3595e7b93b28fffce66c50c#OSW8d40059d9e3951bb97378fe3f119ba21",
                        "Item:OSWb663e6bff3595e7b93b28fffce66c50c#OSW38b0e12539b05ce28cd126c8eea29f95",
                        "Item:OSWb663e6bff3595e7b93b28fffce66c50c#OSW0ec5bf8132b25e58b7032766bd9b3225",
                        "Item:OSWb663e6bff3595e7b93b28fffce66c50c#OSW264ebdc21f54568593a91bbd832b6fbf",
                        "Item:OSWb663e6bff3595e7b93b28fffce66c50c#OSW482939f123595314beca39ad32d65a15",
                        "Item:OSWb663e6bff3595e7b93b28fffce66c50c#OSW5def4be309ce50ee933c99cf4b74e310"
                    ],
                    "x-enum-varnames": [
                        "pascal",
                        "giga_pascal",
                        "deca_pascal",
                        "milli_pascal",
                        "mega_pascal",
                        "kilo_pascal",
                        "hecto_pascal",
                        "micro_pascal"
                    ],
                    "options": {
                        "enum_titles": [
                            "Pa",
                            "GPa",
                            "daPa",
                            "mPa",
                            "MPa",
                            "kPa",
                            "hPa",
                            "μPa"
                        ]
                    },
                    "default": "Item:OSWb663e6bff3595e7b93b28fffce66c50c"
                }
            },
            "defaultProperties": [
                "type"
            ],
            "x-smw-quantity-property": "Property:HasBulkModulusValue"
        }
    },
    "allOf": [
        {
            "$ref": "#/$defs/generated"
        }
    ],
    "title": "BulkModulus",
    "description": "The bulk modulus of a substance measures the substance's resistance to uniform compression. It is defined as the ratio of the infinitesimal pressure increase to the resulting relative decrease of the volume."
}