{
    "type": [
        "Category:OSWac07a46c2cf14f3daec503136861f5ab"
    ],
    "uuid": "3805347e-a7cc-5372-812c-240ee9c72d57",
    "close_ontology_match": [
        "http://qudt.org/vocab/quantitykind/MassOfSolidBooster"
    ],
    "name": "MassOfSolidBooster",
    "label": [
        {
            "text": "Mass Of Solid Booster",
            "lang": "en"
        }
    ],
    "subclass_of": [
        "Category:OSWe9be062de2d15d10891397a18212f920"
    ],
    "quantity_property": "Property:HasMassOfSolidBoosterValue"
}