{
    "@context": [
        "/wiki/Category:OSWea12214400965c818daf0b53062ccf4a?action=raw&slot=jsonschema",
        {}
    ],
    "$defs": {
        "generated": {
            "$comment": "Autogenerated section - do not edit. Generated from Category:Category Category:OSWffe74f291d354037b318c422591c5023 Category:OSWac07a46c2cf14f3daec503136861f5ab",
            "allOf": [
                {
                    "$ref": "/wiki/Category:OSWea12214400965c818daf0b53062ccf4a?action=raw&slot=jsonschema"
                }
            ],
            "type": "object",
            "uuid": "3ba3f32b-c079-55f3-a522-c8159c29a279",
            "title": "GeneratedCO2Equivalent",
            "title*": {
                "en": "CO2Equivalent"
            },
            "description": "This is an autogenerated partial class definition of 'CO2Equivalent'",
            "description*": {
                "en": "The CO2 equivalent is a measure used to compare the emissions from various greenhouse gases \n  on the basis of their global-warming potential (GWP), by converting amounts of other gases to the equivalent amount \n  of carbon dioxide with the same global warming potential."
            },
            "required": [
                "type"
            ],
            "properties": {
                "type": {
                    "default": [
                        "Category:OSW3ba3f32bc07955f3a522c8159c29a279"
                    ]
                },
                "unit": {
                    "format": "autocomplete",
                    "options": {
                        "autocomplete": {
                            "query": "[[-HasUnit::Item:OSW94db60db7d025e5faf85c193158edb5e]][[HasSymbol::like:*{{_user_input}}*]]OR[[-HasPrefixUnit.-HasUnit::Item:OSW94db60db7d025e5faf85c193158edb5e]][[HasSymbol::like:*{{_user_input}}*]]|?HasSymbol=label"
                        }
                    }
                }
            },
            "defaultProperties": [
                "type"
            ]
        }
    },
    "allOf": [
        {
            "$ref": "#/$defs/generated"
        }
    ],
    "title": "CO2Equivalent",
    "description": "The CO2 equivalent is a measure used to compare the emissions from various greenhouse gases \n  on the basis of their global-warming potential (GWP), by converting amounts of other gases to the equivalent amount \n  of carbon dioxide with the same global warming potential."
}