{
    "type": [
        "Category:OSWc7f9aec4f71f4346b6031f96d7e46bd7"
    ],
    "uuid": "4390b219-9b2b-5c6e-aaad-67c7eb19a89a",
    "close_ontology_match": [
        "http://qudt.org/vocab/quantitykind/RestEnergy"
    ],
    "name": "RestEnergy",
    "label": [
        {
            "text": "Rest Energy",
            "lang": "en"
        }
    ],
    "description": [
        {
            "text": "\"Rest Energy\" is the energy equivalent of the rest mass of a body, equal to the rest mass multiplied by the speed of light squared.",
            "lang": "en"
        }
    ],
    "subclass_of": [
        "Category:OSWc87ddd4a7d1159f0a75b686a61ef4e8e"
    ],
    "metaclass": [
        "Category:OSWac07a46c2cf14f3daec503136861f5ab"
    ],
    "quantity": "Item:OSW9018894d8a975b01a1cc94069e45f362"
}