{
    "type": [
        "Category:OSWc7f9aec4f71f4346b6031f96d7e46bd7"
    ],
    "uuid": "487ed07f-775b-5dc2-b0f8-185d06e33fb8",
    "close_ontology_match": [
        "http://qudt.org/vocab/quantitykind/ThermalEnergy",
        "http://dbpedia.org/resource/Thermal_energy"
    ],
    "name": "ThermalEnergy",
    "label": [
        {
            "text": "Thermal Energy",
            "lang": "en"
        }
    ],
    "description": [
        {
            "text": "\"Thermal Energy\" is the portion of the thermodynamic or internal energy of a system that is responsible for the temperature of the system. From a macroscopic thermodynamic description, the thermal energy of a system is given by its constant volume specific heat capacity C(T), a temperature coefficient also called thermal capacity, at any given absolute temperature (T): $U_{thermal} = C(T) \\cdot T$.",
            "lang": "en"
        }
    ],
    "subclass_of": [
        "Category:OSWc87ddd4a7d1159f0a75b686a61ef4e8e"
    ],
    "metaclass": [
        "Category:OSWac07a46c2cf14f3daec503136861f5ab"
    ],
    "quantity": "Item:OSWda64e30338dd5c3fadd232b7708f3b1f"
}