{
    "type": [
        "Category:OSWac07a46c2cf14f3daec503136861f5ab"
    ],
    "uuid": "6ea9da91-7989-54da-a6d0-059bfba4ddbe",
    "close_ontology_match": [
        "http://qudt.org/vocab/quantitykind/NozzleThroatPressure"
    ],
    "name": "NozzleThroatPressure",
    "label": [
        {
            "text": "Nozzle Throat Pressure",
            "lang": "en"
        }
    ],
    "subclass_of": [
        "Category:OSWb58cb5a4654f52e1804c74c035d21352"
    ],
    "quantity_property": "Property:HasNozzleThroatPressureValue"
}