{
    "@context": [
        "/wiki/Category:OSW4082937906634af992cf9a1b18d772cf?action=raw&slot=jsonschema",
        {}
    ],
    "$defs": {
        "generated": {
            "$comment": "Autogenerated section - do not edit. Generated from Category:Category Category:OSWffe74f291d354037b318c422591c5023 Category:OSWc7f9aec4f71f4346b6031f96d7e46bd7",
            "allOf": [
                {
                    "$ref": "/wiki/Category:OSW4082937906634af992cf9a1b18d772cf?action=raw&slot=jsonschema"
                }
            ],
            "type": "object",
            "uuid": "f5c54cd7-0ddf-5ff3-b1ef-1aee6ae8f0cb",
            "title": "GeneratedVolume",
            "title*": {
                "en": "Volume"
            },
            "description": "This is an autogenerated partial class definition of 'Volume'",
            "description*": {
                "en": "The volume of a solid object is the three-dimensional concept of how much space it occupies, often quantified numerically. One-dimensional figures (such as lines) and two-dimensional shapes (such as squares) are assigned zero volume in the three-dimensional space."
            },
            "required": [
                "type"
            ],
            "properties": {
                "type": {
                    "default": [
                        "Category:OSWf5c54cd70ddf5ff3b1ef1aee6ae8f0cb"
                    ]
                },
                "unit": {
                    "format": "autocomplete",
                    "options": {
                        "autocomplete": {
                            "query": "[[-HasUnit::Item:OSW0873fa0d5d7c57bd9428a88c88307847]][[HasSymbol::like:*{{_user_input}}*]]OR[[-HasPrefixUnit.-HasUnit::Item:OSW0873fa0d5d7c57bd9428a88c88307847]][[HasSymbol::like:*{{_user_input}}*]]|?HasSymbol=label"
                        }
                    }
                }
            },
            "defaultProperties": [
                "type"
            ]
        }
    },
    "allOf": [
        {
            "$ref": "#/$defs/generated"
        }
    ],
    "title": "Volume",
    "description": "The volume of a solid object is the three-dimensional concept of how much space it occupies, often quantified numerically. One-dimensional figures (such as lines) and two-dimensional shapes (such as squares) are assigned zero volume in the three-dimensional space."
}